Topsis_Bhuvnesh_101903607.py
Topsis_Bhuvnesh_101903607-0.0.2.dist-info/LICENSE
Topsis_Bhuvnesh_101903607-0.0.2.dist-info/METADATA
Topsis_Bhuvnesh_101903607-0.0.2.dist-info/WHEEL
Topsis_Bhuvnesh_101903607-0.0.2.dist-info/top_level.txt
Topsis_Bhuvnesh_101903607-0.0.2.dist-info/RECORD
