Metadata-Version: 2.1
Name: Topsis-Bhuvnesh-101903607
Version: 0.0.2
Summary: Topsis package by Bhuvnesh Jindal-101903607-3CO23
Home-page: UNKNOWN
Author: Bhuvnesh Jindal
License: UNKNOWN
Keywords: bhuvnesh jindal,tiet,topsis
Platform: UNKNOWN
Classifier: Programming Language :: Python :: 3
Classifier: License :: OSI Approved :: MIT License
Classifier: Operating System :: OS Independent
Requires-Python: >=3.6
Requires-Dist: pandas
